{
    "tournaments": {
        "1": {
            "name": "familial",
            "place": "28260 anet",
            "start": "12/05/2021",
            "end": "05/21/2021, 13:54:30",
            "time_control": "bullet",
            "players": [
                {
                    "name": "Berniche",
                    "first_name": "Aurelie",
                    "birthday": "07/09/1981",
                    "gender": "F",
                    "Elo_rating": 10,
                    "identification number": "Ber10",
                    "score": 4,
                    "opponents": [
                        "Har50",
                        "Dup20",
                        "Hub30",
                        "And40"
                    ]
                },
                {
                    "name": "Dupont",
                    "first_name": "Virginie",
                    "birthday": "03/06/1975",
                    "gender": "F",
                    "Elo_rating": 20,
                    "identification number": "Dup20",
                    "score": 3,
                    "opponents": [
                        "Dup60",
                        "Ber10",
                        "And40",
                        "Hub30"
                    ]
                },
                {
                    "name": "Hubert",
                    "first_name": "Jean-Nicolas",
                    "birthday": "25/10/1979",
                    "gender": "M",
                    "Elo_rating": 30,
                    "identification number": "Hub30",
                    "score": 2,
                    "opponents": [
                        "Car70",
                        "And40",
                        "Ber10",
                        "Dup20"
                    ]
                },
                {
                    "name": "Andre",
                    "first_name": "Frederic",
                    "birthday": "12/02/74",
                    "gender": "M",
                    "Elo_rating": 40,
                    "identification number": "And40",
                    "score": 1,
                    "opponents": [
                        "Bou80",
                        "Hub30",
                        "Dup20",
                        "Ber10"
                    ]
                },
                {
                    "name": "Harnichard",
                    "first_name": "Jocelyne",
                    "birthday": "27/09/1954",
                    "gender": "F",
                    "Elo_rating": 50,
                    "identification number": "Har50",
                    "score": 3,
                    "opponents": [
                        "Ber10",
                        "Dup60",
                        "Car70",
                        "Bou80"
                    ]
                },
                {
                    "name": "Dupre",
                    "first_name": "Jean-Michel",
                    "birthday": "31/08/1951",
                    "gender": "M",
                    "Elo_rating": 60,
                    "identification number": "Dup60",
                    "score": 2,
                    "opponents": [
                        "Dup20",
                        "Har50",
                        "Bou80",
                        "Car70"
                    ]
                },
                {
                    "name": "Carpentier",
                    "first_name": "Melanie",
                    "birthday": "15/01/78",
                    "gender": "F",
                    "Elo_rating": 70,
                    "identification number": "Car70",
                    "score": 1,
                    "opponents": [
                        "Hub30",
                        "Bou80",
                        "Har50",
                        "Dup60"
                    ]
                },
                {
                    "name": "Bourienne",
                    "first_name": "Valentin",
                    "birthday": "04/09/2002",
                    "gender": "M",
                    "Elo_rating": 80,
                    "identification number": "Bou80",
                    "score": 0,
                    "opponents": [
                        "And40",
                        "Car70",
                        "Dup60",
                        "Har50"
                    ]
                }
            ],
            "rounds": [
                {
                    "number": "1",
                    "start": "05/21/2021, 13:54:19",
                    "end": "05/21/2021, 13:54:19",
                    "matchs": [
                        {
                            "player1": {
                                "name": "Berniche",
                                "first_name": "Aurelie",
                                "birthday": "07/09/1981",
                                "gender": "F",
                                "Elo_rating": 10,
                                "identification number": "Ber10",
                                "score": 4,
                                "opponents": [
                                    "Har50",
                                    "Dup20",
                                    "Hub30",
                                    "And40"
                                ]
                            },
                            "player2": {
                                "name": "Harnichard",
                                "first_name": "Jocelyne",
                                "birthday": "27/09/1954",
                                "gender": "F",
                                "Elo_rating": 50,
                                "identification number": "Har50",
                                "score": 3,
                                "opponents": [
                                    "Ber10",
                                    "Dup60",
                                    "Car70",
                                    "Bou80"
                                ]
                            },
                            "score_player1": 1,
                            "score_player2": 0
                        },
                        {
                            "player1": {
                                "name": "Dupont",
                                "first_name": "Virginie",
                                "birthday": "03/06/1975",
                                "gender": "F",
                                "Elo_rating": 20,
                                "identification number": "Dup20",
                                "score": 3,
                                "opponents": [
                                    "Dup60",
                                    "Ber10",
                                    "And40",
                                    "Hub30"
                                ]
                            },
                            "player2": {
                                "name": "Dupre",
                                "first_name": "Jean-Michel",
                                "birthday": "31/08/1951",
                                "gender": "M",
                                "Elo_rating": 60,
                                "identification number": "Dup60",
                                "score": 2,
                                "opponents": [
                                    "Dup20",
                                    "Har50",
                                    "Bou80",
                                    "Car70"
                                ]
                            },
                            "score_player1": 1,
                            "score_player2": 0
                        },
                        {
                            "player1": {
                                "name": "Hubert",
                                "first_name": "Jean-Nicolas",
                                "birthday": "25/10/1979",
                                "gender": "M",
                                "Elo_rating": 30,
                                "identification number": "Hub30",
                                "score": 2,
                                "opponents": [
                                    "Car70",
                                    "And40",
                                    "Ber10",
                                    "Dup20"
                                ]
                            },
                            "player2": {
                                "name": "Carpentier",
                                "first_name": "Melanie",
                                "birthday": "15/01/78",
                                "gender": "F",
                                "Elo_rating": 70,
                                "identification number": "Car70",
                                "score": 1,
                                "opponents": [
                                    "Hub30",
                                    "Bou80",
                                    "Har50",
                                    "Dup60"
                                ]
                            },
                            "score_player1": 1,
                            "score_player2": 0
                        },
                        {
                            "player1": {
                                "name": "Andre",
                                "first_name": "Frederic",
                                "birthday": "12/02/74",
                                "gender": "M",
                                "Elo_rating": 40,
                                "identification number": "And40",
                                "score": 1,
                                "opponents": [
                                    "Bou80",
                                    "Hub30",
                                    "Dup20",
                                    "Ber10"
                                ]
                            },
                            "player2": {
                                "name": "Bourienne",
                                "first_name": "Valentin",
                                "birthday": "04/09/2002",
                                "gender": "M",
                                "Elo_rating": 80,
                                "identification number": "Bou80",
                                "score": 0,
                                "opponents": [
                                    "And40",
                                    "Car70",
                                    "Dup60",
                                    "Har50"
                                ]
                            },
                            "score_player1": 1,
                            "score_player2": 0
                        }
                    ]
                },
                {
                    "number": 2,
                    "start": "05/21/2021, 13:54:23",
                    "end": "05/21/2021, 13:54:23",
                    "matchs": [
                        {
                            "player1": {
                                "name": "Berniche",
                                "first_name": "Aurelie",
                                "birthday": "07/09/1981",
                                "gender": "F",
                                "Elo_rating": 10,
                                "identification number": "Ber10",
                                "score": 4,
                                "opponents": [
                                    "Har50",
                                    "Dup20",
                                    "Hub30",
                                    "And40"
                                ]
                            },
                            "player2": {
                                "name": "Dupont",
                                "first_name": "Virginie",
                                "birthday": "03/06/1975",
                                "gender": "F",
                                "Elo_rating": 20,
                                "identification number": "Dup20",
                                "score": 3,
                                "opponents": [
                                    "Dup60",
                                    "Ber10",
                                    "And40",
                                    "Hub30"
                                ]
                            },
                            "score_player1": 1,
                            "score_player2": 0
                        },
                        {
                            "player1": {
                                "name": "Hubert",
                                "first_name": "Jean-Nicolas",
                                "birthday": "25/10/1979",
                                "gender": "M",
                                "Elo_rating": 30,
                                "identification number": "Hub30",
                                "score": 2,
                                "opponents": [
                                    "Car70",
                                    "And40",
                                    "Ber10",
                                    "Dup20"
                                ]
                            },
                            "player2": {
                                "name": "Andre",
                                "first_name": "Frederic",
                                "birthday": "12/02/74",
                                "gender": "M",
                                "Elo_rating": 40,
                                "identification number": "And40",
                                "score": 1,
                                "opponents": [
                                    "Bou80",
                                    "Hub30",
                                    "Dup20",
                                    "Ber10"
                                ]
                            },
                            "score_player1": 1,
                            "score_player2": 0
                        },
                        {
                            "player1": {
                                "name": "Harnichard",
                                "first_name": "Jocelyne",
                                "birthday": "27/09/1954",
                                "gender": "F",
                                "Elo_rating": 50,
                                "identification number": "Har50",
                                "score": 3,
                                "opponents": [
                                    "Ber10",
                                    "Dup60",
                                    "Car70",
                                    "Bou80"
                                ]
                            },
                            "player2": {
                                "name": "Dupre",
                                "first_name": "Jean-Michel",
                                "birthday": "31/08/1951",
                                "gender": "M",
                                "Elo_rating": 60,
                                "identification number": "Dup60",
                                "score": 2,
                                "opponents": [
                                    "Dup20",
                                    "Har50",
                                    "Bou80",
                                    "Car70"
                                ]
                            },
                            "score_player1": 1,
                            "score_player2": 0
                        },
                        {
                            "player1": {
                                "name": "Carpentier",
                                "first_name": "Melanie",
                                "birthday": "15/01/78",
                                "gender": "F",
                                "Elo_rating": 70,
                                "identification number": "Car70",
                                "score": 1,
                                "opponents": [
                                    "Hub30",
                                    "Bou80",
                                    "Har50",
                                    "Dup60"
                                ]
                            },
                            "player2": {
                                "name": "Bourienne",
                                "first_name": "Valentin",
                                "birthday": "04/09/2002",
                                "gender": "M",
                                "Elo_rating": 80,
                                "identification number": "Bou80",
                                "score": 0,
                                "opponents": [
                                    "And40",
                                    "Car70",
                                    "Dup60",
                                    "Har50"
                                ]
                            },
                            "score_player1": 1,
                            "score_player2": 0
                        }
                    ]
                },
                {
                    "number": 3,
                    "start": "05/21/2021, 13:54:25",
                    "end": "05/21/2021, 13:54:25",
                    "matchs": [
                        {
                            "player1": {
                                "name": "Berniche",
                                "first_name": "Aurelie",
                                "birthday": "07/09/1981",
                                "gender": "F",
                                "Elo_rating": 10,
                                "identification number": "Ber10",
                                "score": 4,
                                "opponents": [
                                    "Har50",
                                    "Dup20",
                                    "Hub30",
                                    "And40"
                                ]
                            },
                            "player2": {
                                "name": "Hubert",
                                "first_name": "Jean-Nicolas",
                                "birthday": "25/10/1979",
                                "gender": "M",
                                "Elo_rating": 30,
                                "identification number": "Hub30",
                                "score": 2,
                                "opponents": [
                                    "Car70",
                                    "And40",
                                    "Ber10",
                                    "Dup20"
                                ]
                            },
                            "score_player1": 1,
                            "score_player2": 0
                        },
                        {
                            "player1": {
                                "name": "Dupont",
                                "first_name": "Virginie",
                                "birthday": "03/06/1975",
                                "gender": "F",
                                "Elo_rating": 20,
                                "identification number": "Dup20",
                                "score": 3,
                                "opponents": [
                                    "Dup60",
                                    "Ber10",
                                    "And40",
                                    "Hub30"
                                ]
                            },
                            "player2": {
                                "name": "Andre",
                                "first_name": "Frederic",
                                "birthday": "12/02/74",
                                "gender": "M",
                                "Elo_rating": 40,
                                "identification number": "And40",
                                "score": 1,
                                "opponents": [
                                    "Bou80",
                                    "Hub30",
                                    "Dup20",
                                    "Ber10"
                                ]
                            },
                            "score_player1": 1,
                            "score_player2": 0
                        },
                        {
                            "player1": {
                                "name": "Harnichard",
                                "first_name": "Jocelyne",
                                "birthday": "27/09/1954",
                                "gender": "F",
                                "Elo_rating": 50,
                                "identification number": "Har50",
                                "score": 3,
                                "opponents": [
                                    "Ber10",
                                    "Dup60",
                                    "Car70",
                                    "Bou80"
                                ]
                            },
                            "player2": {
                                "name": "Carpentier",
                                "first_name": "Melanie",
                                "birthday": "15/01/78",
                                "gender": "F",
                                "Elo_rating": 70,
                                "identification number": "Car70",
                                "score": 1,
                                "opponents": [
                                    "Hub30",
                                    "Bou80",
                                    "Har50",
                                    "Dup60"
                                ]
                            },
                            "score_player1": 1,
                            "score_player2": 0
                        },
                        {
                            "player1": {
                                "name": "Dupre",
                                "first_name": "Jean-Michel",
                                "birthday": "31/08/1951",
                                "gender": "M",
                                "Elo_rating": 60,
                                "identification number": "Dup60",
                                "score": 2,
                                "opponents": [
                                    "Dup20",
                                    "Har50",
                                    "Bou80",
                                    "Car70"
                                ]
                            },
                            "player2": {
                                "name": "Bourienne",
                                "first_name": "Valentin",
                                "birthday": "04/09/2002",
                                "gender": "M",
                                "Elo_rating": 80,
                                "identification number": "Bou80",
                                "score": 0,
                                "opponents": [
                                    "And40",
                                    "Car70",
                                    "Dup60",
                                    "Har50"
                                ]
                            },
                            "score_player1": 1,
                            "score_player2": 0
                        }
                    ]
                },
                {
                    "number": 4,
                    "start": "05/21/2021, 13:54:28",
                    "end": "05/21/2021, 13:54:28",
                    "matchs": [
                        {
                            "player1": {
                                "name": "Berniche",
                                "first_name": "Aurelie",
                                "birthday": "07/09/1981",
                                "gender": "F",
                                "Elo_rating": 10,
                                "identification number": "Ber10",
                                "score": 4,
                                "opponents": [
                                    "Har50",
                                    "Dup20",
                                    "Hub30",
                                    "And40"
                                ]
                            },
                            "player2": {
                                "name": "Andre",
                                "first_name": "Frederic",
                                "birthday": "12/02/74",
                                "gender": "M",
                                "Elo_rating": 40,
                                "identification number": "And40",
                                "score": 1,
                                "opponents": [
                                    "Bou80",
                                    "Hub30",
                                    "Dup20",
                                    "Ber10"
                                ]
                            },
                            "score_player1": 1,
                            "score_player2": 0
                        },
                        {
                            "player1": {
                                "name": "Dupont",
                                "first_name": "Virginie",
                                "birthday": "03/06/1975",
                                "gender": "F",
                                "Elo_rating": 20,
                                "identification number": "Dup20",
                                "score": 3,
                                "opponents": [
                                    "Dup60",
                                    "Ber10",
                                    "And40",
                                    "Hub30"
                                ]
                            },
                            "player2": {
                                "name": "Hubert",
                                "first_name": "Jean-Nicolas",
                                "birthday": "25/10/1979",
                                "gender": "M",
                                "Elo_rating": 30,
                                "identification number": "Hub30",
                                "score": 2,
                                "opponents": [
                                    "Car70",
                                    "And40",
                                    "Ber10",
                                    "Dup20"
                                ]
                            },
                            "score_player1": 1,
                            "score_player2": 0
                        },
                        {
                            "player1": {
                                "name": "Harnichard",
                                "first_name": "Jocelyne",
                                "birthday": "27/09/1954",
                                "gender": "F",
                                "Elo_rating": 50,
                                "identification number": "Har50",
                                "score": 3,
                                "opponents": [
                                    "Ber10",
                                    "Dup60",
                                    "Car70",
                                    "Bou80"
                                ]
                            },
                            "player2": {
                                "name": "Bourienne",
                                "first_name": "Valentin",
                                "birthday": "04/09/2002",
                                "gender": "M",
                                "Elo_rating": 80,
                                "identification number": "Bou80",
                                "score": 0,
                                "opponents": [
                                    "And40",
                                    "Car70",
                                    "Dup60",
                                    "Har50"
                                ]
                            },
                            "score_player1": 1,
                            "score_player2": 0
                        },
                        {
                            "player1": {
                                "name": "Dupre",
                                "first_name": "Jean-Michel",
                                "birthday": "31/08/1951",
                                "gender": "M",
                                "Elo_rating": 60,
                                "identification number": "Dup60",
                                "score": 2,
                                "opponents": [
                                    "Dup20",
                                    "Har50",
                                    "Bou80",
                                    "Car70"
                                ]
                            },
                            "player2": {
                                "name": "Carpentier",
                                "first_name": "Melanie",
                                "birthday": "15/01/78",
                                "gender": "F",
                                "Elo_rating": 70,
                                "identification number": "Car70",
                                "score": 1,
                                "opponents": [
                                    "Hub30",
                                    "Bou80",
                                    "Har50",
                                    "Dup60"
                                ]
                            },
                            "score_player1": 1,
                            "score_player2": 0
                        }
                    ]
                }
            ]
        }
    }
}